pcs_scraper/__init__.py
pcs_scraper/race.py
pcs_scraper/rider.py
pcs_scraper/team.py
pcs_scraper/utility/__init__.py
pcs_scraper/utility/convert_data.py
pcs_scraper/utility/input_options.py
pcs_scraper/utility/table_manipulation.py
pcs_scraper/utility/url_management.py
pcs_scraper-0.2.0.dist-info/LICENSE.txt
pcs_scraper-0.2.0.dist-info/METADATA
pcs_scraper-0.2.0.dist-info/WHEEL
pcs_scraper-0.2.0.dist-info/top_level.txt
pcs_scraper-0.2.0.dist-info/RECORD
