Metadata-Version: 2.1
Name: pcs-scraper
Version: 0.2.0
Summary: A python-based api to access procyclingstats data
Home-page: https://github.com/lucaskoensgen/pcs_scraper
Author: Lucas Koensgen
Author-email: l.koensgen@gmail.com
License: GPLv3
Keywords: cycling,web-scraping,statistics,procyclingstats,peloton
Classifier: Development Status :: 3 - Alpha
Classifier: Intended Audience :: Science/Research
Classifier: Intended Audience :: Information Technology
Classifier: Topic :: Scientific/Engineering :: Information Analysis
Classifier: Topic :: Software Development :: Libraries :: Python Modules
Classifier: Topic :: Internet
Classifier: License :: OSI Approved :: GNU General Public License v3 (GPLv3)
Classifier: Programming Language :: Python :: 3.9
Classifier: Operating System :: OS Independent
Requires-Python: >=3.9
License-File: LICENSE.txt
Requires-Dist: requests (>=2.27.1)
Requires-Dist: beautifulsoup4 (>=4.10.0)
Requires-Dist: pandas (>=1.4.1)
